{
    "WTA_1000_DUBAI": [
        {
            "date": "2026-02-12",
            "change": "<strong>MADISON KEYS</strong> removed from Main Draw"
        },
        {
            "date": "2026-02-12",
            "change": "<strong>JELENA OSTAPENKO</strong> removed from Main Draw"
        },
        {
            "date": "2026-02-12",
            "change": "<strong>MAYA JOINT</strong> removed from Main Draw"
        },
        {
            "date": "2026-02-12",
            "change": "<strong>PAULA BADOSA</strong> removed from Main Draw"
        },
        {
            "date": "2026-02-12",
            "change": "<strong>ARYNA SABALENKA</strong> removed from Main Draw"
        },
        {
            "date": "2026-02-12",
            "change": "<strong>LIUDMILA SAMSONOVA</strong> removed from Main Draw"
        },
        {
            "date": "2026-02-12",
            "change": "<strong>MARIE BOUZKOVA</strong> removed from Main Draw"
        },
        {
            "date": "2026-02-12",
            "change": "<strong>JASMINE PAOLINI</strong> removed from Main Draw"
        },
        {
            "date": "2026-02-12",
            "change": "<strong>EMMA RADUCANU</strong> removed from Main Draw"
        },
        {
            "date": "2026-02-12",
            "change": "<strong>ANNA KALINSKAYA</strong> removed from Main Draw"
        },
        {
            "date": "2026-02-12",
            "change": "<strong>JAQUELINE  CRISTIAN</strong> removed from Main Draw"
        },
        {
            "date": "2026-02-12",
            "change": "<strong>CLARA TAUSON</strong> removed from Main Draw"
        },
        {
            "date": "2026-02-12",
            "change": "<strong>EMMA NAVARRO</strong> removed from Main Draw"
        },
        {
            "date": "2026-02-12",
            "change": "<strong>IGA SWIATEK</strong> removed from Main Draw"
        },
        {
            "date": "2026-02-12",
            "change": "<strong>COCO GAUFF</strong> removed from Main Draw"
        },
        {
            "date": "2026-02-12",
            "change": "<strong>EKATERINA ALEXANDROVA</strong> removed from Main Draw"
        },
        {
            "date": "2026-02-12",
            "change": "<strong>BARBORA KREJCIKOVA</strong> removed from Main Draw"
        },
        {
            "date": "2026-02-12",
            "change": "<strong>ELISE MERTENS</strong> removed from Main Draw"
        },
        {
            "date": "2026-02-12",
            "change": "<strong>AMANDA ANISIMOVA</strong> removed from Main Draw"
        },
        {
            "date": "2026-02-12",
            "change": "<strong>DAYANA YASTREMSKA</strong> removed from Main Draw"
        },
        {
            "date": "2026-02-12",
            "change": "<strong>ELENA RYBAKINA</strong> removed from Main Draw"
        },
        {
            "date": "2026-02-12",
            "change": "<strong>KAROLINA PLISKOVA</strong> removed from Main Draw"
        },
        {
            "date": "2026-02-12",
            "change": "<strong>ELINA SVITOLINA</strong> removed from Main Draw"
        },
        {
            "date": "2026-02-12",
            "change": "<strong>LEYLAH FERNANDEZ</strong> removed from Main Draw"
        },
        {
            "date": "2026-02-12",
            "change": "<strong>VICTORIA MBOKO</strong> removed from Main Draw"
        },
        {
            "date": "2026-02-12",
            "change": "<strong>SOFIA KENIN</strong> removed from Main Draw"
        },
        {
            "date": "2026-02-12",
            "change": "<strong>JESSICA PEGULA</strong> removed from Main Draw"
        },
        {
            "date": "2026-02-12",
            "change": "<strong>MCCARTNEY KESSLER</strong> removed from Main Draw"
        },
        {
            "date": "2026-02-12",
            "change": "<strong>TATJANA MARIA</strong> removed from Main Draw"
        },
        {
            "date": "2026-02-12",
            "change": "<strong>IVA JOVIC</strong> removed from Main Draw"
        },
        {
            "date": "2026-02-12",
            "change": "<strong>MARKETA VONDROUSOVA</strong> removed from Main Draw"
        },
        {
            "date": "2026-02-12",
            "change": "<strong>KAROLINA MUCHOVA</strong> removed from Main Draw"
        },
        {
            "date": "2026-02-12",
            "change": "<strong>LINDA NOSKOVA</strong> removed from Main Draw"
        },
        {
            "date": "2026-02-12",
            "change": "<strong>MIRRA ANDREEVA</strong> removed from Main Draw"
        },
        {
            "date": "2026-02-12",
            "change": "<strong>ANN LI</strong> removed from Main Draw"
        },
        {
            "date": "2026-02-12",
            "change": "<strong>JESSICA BOUZAS MANEIRO</strong> removed from Main Draw"
        },
        {
            "date": "2026-02-12",
            "change": "<strong>NAOMI OSAKA</strong> removed from Main Draw"
        },
        {
            "date": "2026-02-12",
            "change": "<strong>BELINDA BENCIC</strong> removed from Main Draw"
        },
        {
            "date": "2026-02-12",
            "change": "<strong>MARTA KOSTYUK</strong> removed from Main Draw"
        },
        {
            "date": "2026-02-12",
            "change": "<strong>DIANA SHNAIDER</strong> removed from Main Draw"
        },
        {
            "date": "2026-02-12",
            "change": "<strong>QINWEN ZHENG</strong> removed from Main Draw"
        },
        {
            "date": "2026-02-12",
            "change": "<strong>DARIA KASATKINA</strong> removed from Main Draw"
        },
        {
            "date": "2026-02-12",
            "change": "<strong>SORANA CIRSTEA</strong> removed from Main Draw"
        },
        {
            "date": "2026-02-04",
            "change": "<strong>LOIS BOISSON</strong> removed from Main Draw"
        },
        {
            "date": "2026-02-04",
            "change": "<strong>VERONIKA KUDERMETOVA</strong> removed from Main Draw"
        },
        {
            "date": "2026-02-04",
            "change": "<strong>DARIA KASATKINA</strong> added to Main Draw"
        },
        {
            "date": "2026-02-04",
            "change": "<strong>MARIE BOUZKOVA</strong> added to Main Draw"
        },
        {
            "date": "2026-02-04",
            "change": "<strong>ELLA SEIDEL</strong> added to Qualifying"
        },
        {
            "date": "2026-02-04",
            "change": "<strong>CAMILA OSORIO</strong> added to Qualifying"
        },
        {
            "date": "2026-01-31",
            "change": "<strong>EVA LYS</strong> removed from Main Draw"
        },
        {
            "date": "2026-01-31",
            "change": "<strong>TATJANA MARIA</strong> added to Main Draw"
        }
    ],
    "WTA_125_OEIRAS_2": [
        {
            "date": "2026-02-05",
            "change": "<strong>NIKOLA BARTUNKOVA</strong> removed from Main Draw"
        },
        {
            "date": "2026-02-05",
            "change": "<strong>MARINA STAKUSIC</strong> removed from Main Draw"
        },
        {
            "date": "2026-02-05",
            "change": "<strong>FRANCISCA JORGE</strong> added to Main Draw"
        },
        {
            "date": "2026-02-05",
            "change": "<strong>ANOUK KOEVERMANS</strong> added to Main Draw"
        },
        {
            "date": "2026-02-05",
            "change": "<strong>DALILA JAKUPOVIC</strong> added to Qualifying"
        },
        {
            "date": "2026-02-05",
            "change": "<strong>SARA SORRIBES TORMO</strong> added to Qualifying"
        }
    ],
    "WTA_125_MIDLAND": [
        {
            "date": "2026-02-07",
            "change": "<strong>TATIANA PIERI</strong> removed from Qualifying"
        },
        {
            "date": "2026-02-07",
            "change": "<strong>LIA KARATANCHEVA</strong> removed from Qualifying"
        },
        {
            "date": "2026-02-07",
            "change": "<strong>XIAODI YOU</strong> removed from Qualifying"
        },
        {
            "date": "2026-02-07",
            "change": "<strong>VALERIYA STRAKHOVA</strong> added to Qualifying"
        },
        {
            "date": "2026-02-07",
            "change": "<strong>VICTORIA HU</strong> added to Qualifying"
        },
        {
            "date": "2026-02-07",
            "change": "<strong>MARTINA CAPURRO TABORDA</strong> added to Qualifying"
        },
        {
            "date": "2026-02-07",
            "change": "<strong>BIANCA ANDREESCU</strong> removed from Main Draw"
        },
        {
            "date": "2026-02-07",
            "change": "<strong>HIMENO SAKATSUME</strong> removed from Main Draw"
        },
        {
            "date": "2026-02-07",
            "change": "<strong>LIA KARATANCHEVA</strong> added to Main Draw"
        },
        {
            "date": "2026-02-07",
            "change": "<strong>XIAODI YOU</strong> added to Main Draw"
        },
        {
            "date": "2026-02-05",
            "change": "<strong>FRANCESCA JONES</strong> removed from Main Draw"
        },
        {
            "date": "2026-02-05",
            "change": "<strong>ANNA ROGERS</strong> added to Main Draw"
        },
        {
            "date": "2026-02-05",
            "change": "<strong>MIA RISTIC</strong> removed from Qualifying"
        },
        {
            "date": "2026-02-05",
            "change": "<strong>EMILY APPLETON</strong> added to Qualifying"
        }
    ],
    "WTA_125_ANTALYA_1": [
        {
            "date": "2026-02-06",
            "change": "<strong>LISA PIGATO</strong> removed from Main Draw"
        },
        {
            "date": "2026-02-06",
            "change": "<strong>ALICE RAME</strong> added to Main Draw"
        }
    ]
}